README.md
setup.py
pymarkowitz/Backtester.py
pymarkowitz/Constraints.py
pymarkowitz/Exceptions.py
pymarkowitz/Metrics.py
pymarkowitz/Moments.py
pymarkowitz/Objectives.py
pymarkowitz/Optimizer.py
pymarkowitz/Returns.py
pymarkowitz/__init__.py
pymarkowitz.egg-info/PKG-INFO
pymarkowitz.egg-info/SOURCES.txt
pymarkowitz.egg-info/dependency_links.txt
pymarkowitz.egg-info/not-zip-safe
pymarkowitz.egg-info/requires.txt
pymarkowitz.egg-info/top_level.txt