Metadata-Version: 2.1
Name: pymarkowitz
Version: 1.1.5
Summary: pymarkowitz
Home-page: https://github.com/johnsoong216/pymarkowitz
Author: johnsoong216
Author-email: johnsoong216@hotmail.com
License: MIT
Keywords: portfolio-optimization,finance,mean-variance-optimization
Platform: UNKNOWN
